flux_sci_lang-0.1.0.dist-info/licenses/LICENSE
solvers/__init__.py
solvers/finite_difference.py
solvers/gpu_acceleration.py
solvers/navier_stokes.py
solvers/validation.py
flux_sci_lang-0.1.0.dist-info/METADATA
flux_sci_lang-0.1.0.dist-info/WHEEL
flux_sci_lang-0.1.0.dist-info/entry_points.txt
flux_sci_lang-0.1.0.dist-info/top_level.txt
flux_sci_lang-0.1.0.dist-info/RECORD
