Metadata-Version: 2.4
Name: flux-sci-lang
Version: 0.1.0
Summary: FLUX Scientific Computing Language - Domain-Specific Language for PDEs, CFD, and Computational Physics
Home-page: https://github.com/MichaelCrowe11/flux-scientific
Author: Michael Crowe
Author-email: Michael Crowe <michael@flux-sci.org>
License: MIT
Project-URL: Homepage, https://github.com/MichaelCrowe11/flux-sci-lang
Project-URL: Documentation, https://flux-sci-lang.readthedocs.io
Project-URL: Repository, https://github.com/MichaelCrowe11/flux-sci-lang
Project-URL: Bug Tracker, https://github.com/MichaelCrowe11/flux-sci-lang/issues
Keywords: scientific-computing,PDE,CFD,DSL,computational-physics,finite-element,GPU
Classifier: Development Status :: 3 - Alpha
Classifier: Intended Audience :: Science/Research
Classifier: Topic :: Scientific/Engineering :: Physics
Classifier: Topic :: Scientific/Engineering :: Mathematics
Classifier: License :: OSI Approved :: MIT License
Classifier: Programming Language :: Python :: 3
Classifier: Programming Language :: Python :: 3.8
Classifier: Programming Language :: Python :: 3.9
Classifier: Programming Language :: Python :: 3.10
Classifier: Programming Language :: Python :: 3.11
Requires-Python: >=3.8
License-File: LICENSE
Requires-Dist: numpy>=1.20.0
Requires-Dist: scipy>=1.7.0
Requires-Dist: matplotlib>=3.3.0
Provides-Extra: dev
Requires-Dist: pytest>=7.0; extra == "dev"
Requires-Dist: pytest-cov>=3.0; extra == "dev"
Requires-Dist: black>=22.0; extra == "dev"
Requires-Dist: flake8>=5.0; extra == "dev"
Requires-Dist: mypy>=0.990; extra == "dev"
Requires-Dist: sphinx>=4.0; extra == "dev"
Requires-Dist: sphinx-rtd-theme>=1.0; extra == "dev"
Provides-Extra: gpu
Requires-Dist: cupy>=10.0; extra == "gpu"
Requires-Dist: pycuda>=2021.1; extra == "gpu"
Provides-Extra: hpc
Requires-Dist: mpi4py>=3.0; extra == "hpc"
Requires-Dist: h5py>=3.0; extra == "hpc"
Dynamic: author
Dynamic: home-page
Dynamic: license-file
Dynamic: requires-python
